{"_type":"export","__export_format":4,"__export_date":"2022-02-03T22:03:55.038Z","__export_source":"insomnia.desktop.app:v2021.7.2","resources":[{"_id":"req_147edea57708449eb38a33c7791cb881","parentId":"fld_b8dc2f7ef783426183caa42d27f6e457","modified":1643925806221,"created":1616466766759,"url":"{{baseURL}}/{{resource}}","name":"Create","description":"","method":"POST","body":{"mimeType":"application/json","text":"{ \n  \"username\": \"teste\",\n\t\"name\": \"User 1\",\n\t\"email\": \"user@gmail.com\",\n\t\"driver_license\": \"123456\",\n\t\"password\": \"123456\"\n}\n"},"parameters":[],"headers":[{"name":"Content-Type","value":"application/json","id":"pair_ae1dac98dd684be695d0657636066c91"}],"authentication":{},"metaSortKey":-1616466766759,"isPrivate":false,"settingStoreCookies":true,"settingSendCookies":true,"settingDisableRenderRequestBody":false,"settingEncodeUrl":true,"settingRebuildPath":true,"settingFollowRedirects":"global","_type":"request"},{"_id":"fld_b8dc2f7ef783426183caa42d27f6e457","parentId":"wrk_c323334f50894ea5bf086585c0dc8307","modified":1616466787977,"created":1616466761877,"name":"Users","description":"","environment":{"resource":"users"},"environmentPropertyOrder":{"&":["resource"]},"metaSortKey":-1616466761877,"_type":"request_group"},{"_id":"wrk_c323334f50894ea5bf086585c0dc8307","parentId":null,"modified":1615924948129,"created":1615823156049,"name":"RentX","description":"","scope":"collection","_type":"workspace"},{"_id":"req_0121ba3092e94f84819f344a84f28cd6","parentId":"fld_b8dc2f7ef783426183caa42d27f6e457","modified":1643925799133,"created":1616554404301,"url":"{{baseURL}}/{{resource}}/avatar","name":"Update Avatar","description":"","method":"PATCH","body":{"mimeType":"multipart/form-data","params":[{"name":"avatar","value":"","description":"","id":"pair_77c6df9f386f419a895292e424e92490","type":"file","fileName":"/Users/eliasgcf/Pictures/profile.jpg","disabled":false}]},"parameters":[],"headers":[{"name":"Content-Type","value":"multipart/form-data","id":"pair_69c6183720b842d58e0792ca0adffab0"}],"authentication":{"type":"bearer","token":"{{userToken}}"},"metaSortKey":-1616466766709,"isPrivate":false,"settingStoreCookies":true,"settingSendCookies":true,"settingDisableRenderRequestBody":false,"settingEncodeUrl":true,"settingRebuildPath":true,"settingFollowRedirects":"global","_type":"request"},{"_id":"req_846d403b0a8a4232b7197ec032607398","parentId":"fld_b8dc2f7ef783426183caa42d27f6e457","modified":1643925797920,"created":1618361562097,"url":"{{baseURL}}/{{resource}}/profile","name":"Profile","description":"","method":"GET","body":{},"parameters":[],"headers":[],"authentication":{"type":"bearer","token":"{{userToken}}"},"metaSortKey":-1616466766684,"isPrivate":false,"settingStoreCookies":true,"settingSendCookies":true,"settingDisableRenderRequestBody":false,"settingEncodeUrl":true,"settingRebuildPath":true,"settingFollowRedirects":"global","_type":"request"},{"_id":"req_30a39f0577364a2a9ff57285b9f8daab","parentId":"fld_a262f06643714aeb81e6007df98bad2b","modified":1643925796726,"created":1617927929178,"url":"{{baseURL}}/{{resource}}/forgot","name":"Send Forgot Mail","description":"","method":"POST","body":{"mimeType":"application/json","text":"{\n\t\"email\": \"user@gmail.com\"\n}"},"parameters":[],"headers":[{"name":"Content-Type","value":"application/json","id":"pair_d67ffee32bbf4cc199f28e538184e9bb"}],"authentication":{},"metaSortKey":-1617927929178,"isPrivate":false,"settingStoreCookies":true,"settingSendCookies":true,"settingDisableRenderRequestBody":false,"settingEncodeUrl":true,"settingRebuildPath":true,"settingFollowRedirects":"global","_type":"request"},{"_id":"fld_a262f06643714aeb81e6007df98bad2b","parentId":"fld_b8dc2f7ef783426183caa42d27f6e457","modified":1617927908963,"created":1617927886548,"name":"Password","description":"","environment":{"resource":"password"},"environmentPropertyOrder":{"&":["resource"]},"metaSortKey":-1616466766659,"_type":"request_group"},{"_id":"req_f28bed11b65b4f3bb352ed36dea7cad6","parentId":"fld_a262f06643714aeb81e6007df98bad2b","modified":1643925795550,"created":1617932662413,"url":"{{baseURL}}/{{resource}}/reset","name":"Reset Password","description":"","method":"POST","body":{"mimeType":"application/json","text":"{\n\t\"password\": \"teste\"\n}"},"parameters":[{"id":"pair_f03594d57d0d423b824a515bb89b5b56","name":"token","value":"c9499749-329b-43f0-971f-e3903699ae3a","description":""}],"headers":[{"name":"Content-Type","value":"application/json","id":"pair_d67ffee32bbf4cc199f28e538184e9bb"}],"authentication":{},"metaSortKey":-1617716214104.5,"isPrivate":false,"settingStoreCookies":true,"settingSendCookies":true,"settingDisableRenderRequestBody":false,"settingEncodeUrl":true,"settingRebuildPath":true,"settingFollowRedirects":"global","_type":"request"},{"_id":"req_027c24f4796e45548af76c1306293b0a","parentId":"fld_3f1a6f62a70c4298b467ca298abcea42","modified":1643925794168,"created":1616547437737,"url":"{{baseURL}}/{{resource}}","name":"Authenticate","description":"","method":"POST","body":{"mimeType":"application/json","text":"{\n\t\"email\": \"user@gmail.com\",\n\t\"password\": \"123456\"\n}"},"parameters":[],"headers":[{"name":"Content-Type","value":"application/json","id":"pair_627087b2d8a640999b369c7b290873df"}],"authentication":{},"metaSortKey":-1616547437737,"isPrivate":false,"settingStoreCookies":true,"settingSendCookies":true,"settingDisableRenderRequestBody":false,"settingEncodeUrl":true,"settingRebuildPath":true,"settingFollowRedirects":"global","_type":"request"},{"_id":"fld_3f1a6f62a70c4298b467ca298abcea42","parentId":"wrk_c323334f50894ea5bf086585c0dc8307","modified":1617845650324,"created":1616547429149,"name":"Sessions","description":"","environment":{"resource":"sessions"},"environmentPropertyOrder":{"&":["resource"]},"metaSortKey":-1616426908227.6875,"_type":"request_group"},{"_id":"req_b167990393c84eacb04535acb5b7ed19","parentId":"fld_3f1a6f62a70c4298b467ca298abcea42","modified":1643925793557,"created":1617154964103,"url":"{{baseURL}}/{{resource}}","name":"Admin Authenticate","description":"","method":"POST","body":{"mimeType":"application/json","text":"{\n\t\"email\": \"admin@rentx.com.br\",\n\t\"password\": \"admin\"\n}"},"parameters":[],"headers":[{"name":"Content-Type","value":"application/json","id":"pair_627087b2d8a640999b369c7b290873df"}],"authentication":{},"metaSortKey":-1616507102248,"isPrivate":false,"settingStoreCookies":true,"settingSendCookies":true,"settingDisableRenderRequestBody":false,"settingEncodeUrl":true,"settingRebuildPath":true,"settingFollowRedirects":"global","_type":"request"},{"_id":"req_596e311068d44fcb883331f3642ed2a8","parentId":"fld_3f1a6f62a70c4298b467ca298abcea42","modified":1643925791412,"created":1617845676894,"url":"{{baseURL}}/refresh-token","name":"Craete Refresh Token","description":"","method":"POST","body":{"mimeType":"application/json","text":"{\n\t\"token\": \"eyJhbGciOiJIUzI1NiIsInR5cCI6IkpXVCJ9.eyJlbWFpbCI6InVzZXJAZ21haWwuY29tIiwiaWF0IjoxNjI5NDExNzM3LCJleHAiOjE2MzIwMDM3MzcsInN1YiI6ImMzYjM0YzY1LTZkYjktNGQxOS04NDZjLTZmZmI3YTc3NzIyMyJ9.hdpjTgayZA58tH_gGMh401nne9hCh5Rf96QBmqf9lJ4\"\n}"},"parameters":[],"headers":[{"name":"Content-Type","value":"application/json","id":"pair_42dabd8c56b94607a41ef9cbd3147120"}],"authentication":{},"metaSortKey":-1616507102198,"isPrivate":false,"settingStoreCookies":true,"settingSendCookies":true,"settingDisableRenderRequestBody":false,"settingEncodeUrl":true,"settingRebuildPath":true,"settingFollowRedirects":"global","_type":"request"},{"_id":"req_df520c258a46446da283edc9ca15378f","parentId":"fld_6fce0cf00902477dbb6f7168a70694d2","modified":1643925789340,"created":1615824040227,"url":"{{baseURL}}/{{resource}}","name":"Create","description":"","method":"POST","body":{"mimeType":"application/json","text":"{\n\t\"name\": \"123\",\n\t\"description\": \"Testeasdf\"\n}"},"parameters":[],"headers":[{"name":"Content-Type","value":"application/json","id":"pair_7627baaec5d84278a294eac6e15aafe7"}],"authentication":{"type":"bearer","token":"{{adminToken}}"},"metaSortKey":-1615825661230,"isPrivate":false,"settingStoreCookies":true,"settingSendCookies":true,"settingDisableRenderRequestBody":false,"settingEncodeUrl":true,"settingRebuildPath":true,"settingFollowRedirects":"global","_type":"request"},{"_id":"fld_6fce0cf00902477dbb6f7168a70694d2","parentId":"wrk_c323334f50894ea5bf086585c0dc8307","modified":1617670492051,"created":1615824009259,"name":"Categories","description":"","environment":{"resource":"categories"},"environmentPropertyOrder":{"&":["resource"]},"metaSortKey":-1616387054578.375,"_type":"request_group"},{"_id":"req_7b6c9c00c6e3438f90a1f5e7ebd4a762","parentId":"fld_6fce0cf00902477dbb6f7168a70694d2","modified":1615825667271,"created":1615825661180,"url":"{{baseURL}}/{{resource}}","name":"List All","description":"","method":"GET","body":{},"parameters":[],"headers":[],"authentication":{},"metaSortKey":-1615825661180,"isPrivate":false,"settingStoreCookies":true,"settingSendCookies":true,"settingDisableRenderRequestBody":false,"settingEncodeUrl":true,"settingRebuildPath":true,"settingFollowRedirects":"global","_type":"request"},{"_id":"req_d500f17d60a14764bdbaef2639b558d1","parentId":"fld_6fce0cf00902477dbb6f7168a70694d2","modified":1642106902957,"created":1615853742336,"url":"{{baseURL}}/{{resource}}/import","name":"Import","description":"","method":"POST","body":{"mimeType":"multipart/form-data","params":[{"name":"file","value":"","description":"","id":"pair_6777384131bb4d52a645bb1fc6442781","type":"file","fileName":"/Users/eliasgcf/Documents/arquivo.csv","disabled":false}]},"parameters":[],"headers":[{"name":"Content-Type","value":"multipart/form-data","id":"pair_0affbe887d404c83a27e0fb8d3c1c592"}],"authentication":{},"metaSortKey":-1615825661130,"isPrivate":false,"settingStoreCookies":true,"settingSendCookies":true,"settingDisableRenderRequestBody":false,"settingEncodeUrl":true,"settingRebuildPath":true,"settingFollowRedirects":"global","_type":"request"},{"_id":"req_c51caffa636b4774bdcd602da49b3f7e","parentId":"fld_b4ead2a148524277ad48a8d61e2ab9fb","modified":1643925766579,"created":1617152119038,"url":"{{baseURL}}/{{resource}}","name":"Create","description":"","method":"POST","body":{"mimeType":"application/json","text":"{\n\t\"name\": \"Car Name 4\",\n\t\"description\": \"Car5 Description\",\n\t\"daily_rate\": 100,\n\t\"license_plate\": \"ABC-3131\",\n\t\"fine_amount\": 10,\n\t\"category_id\": \"f052d55b-4be7-4ded-88bf-3decc0a2abb5\",\n\t\"brand\": \"Brand3\"\n}"},"parameters":[],"headers":[{"name":"Content-Type","value":"application/json","id":"pair_f68351b4b4654b11928721f5ae2be003"}],"authentication":{"type":"bearer","token":"{{adminToken}}"},"metaSortKey":-1617238818263,"isPrivate":false,"settingStoreCookies":true,"settingSendCookies":true,"settingDisableRenderRequestBody":false,"settingEncodeUrl":true,"settingRebuildPath":true,"settingFollowRedirects":"global","_type":"request"},{"_id":"fld_b4ead2a148524277ad48a8d61e2ab9fb","parentId":"wrk_c323334f50894ea5bf086585c0dc8307","modified":1617670489231,"created":1617152110897,"name":"Cars","description":"","environment":{"resource":"cars"},"environmentPropertyOrder":{"&":["resource"]},"metaSortKey":-1616307347279.75,"_type":"request_group"},{"_id":"req_2d4bcd7ccdd346e7803b4b72daa439c3","parentId":"fld_b4ead2a148524277ad48a8d61e2ab9fb","modified":1643925765770,"created":1617292681173,"url":"{{baseURL}}/{{resource}}/specifications/f15fb349-cf19-43dc-a243-f4da4d217bc2","name":"Create Specifications","description":"","method":"POST","body":{"mimeType":"application/json","text":"{\n\t\"specifications_id\": [\n\t\t\"5dd75b8f-ed94-46ca-8371-7ea515cab986\"\n\t]\n}"},"parameters":[],"headers":[{"name":"Content-Type","value":"application/json","id":"pair_05b79bc0e0d5413b8a4bca83c084c758"}],"authentication":{"type":"bearer","token":"{{adminToken}}"},"metaSortKey":-1617238818238,"isPrivate":false,"settingStoreCookies":true,"settingSendCookies":true,"settingDisableRenderRequestBody":false,"settingEncodeUrl":true,"settingRebuildPath":true,"settingFollowRedirects":"global","_type":"request"},{"_id":"req_2ba5fcb4f14b4c04a8ec41008e037da2","parentId":"fld_b4ead2a148524277ad48a8d61e2ab9fb","modified":1643925765071,"created":1617297417628,"url":"{{baseURL}}/{{resource}}/images/ed6b5dbd-0187-491a-bb5d-e3c36111a9ac","name":"Upload Images","description":"","method":"POST","body":{"mimeType":"multipart/form-data","params":[{"name":"images","value":"","description":"","id":"pair_cdd731a2307647b2b3f28368d26c5961","type":"file","fileName":"/Users/eliasgcf/Documents/carro1.jpg","disabled":false},{"name":"images","value":"","description":"","id":"pair_7f536821a9324ef2852838bc4370e78c","type":"file","fileName":"/Users/eliasgcf/Documents/carro2.jpg","disabled":false}]},"parameters":[],"headers":[{"name":"Content-Type","value":"multipart/form-data","id":"pair_beed2b74526a41b39b2df04038f035cc"}],"authentication":{"type":"bearer","token":"{{adminToken}}"},"metaSortKey":-1617238818225.5,"isPrivate":false,"settingStoreCookies":true,"settingSendCookies":true,"settingDisableRenderRequestBody":false,"settingEncodeUrl":true,"settingRebuildPath":true,"settingFollowRedirects":"global","_type":"request"},{"_id":"req_a121c7e352b54a2393c08e6741e6475f","parentId":"fld_b4ead2a148524277ad48a8d61e2ab9fb","modified":1624459254131,"created":1617238818213,"url":"{{baseURL}}/{{resource}}/available","name":"List All Available","description":"","method":"GET","body":{},"parameters":[{"name":"name","value":"Car Name 3","description":"","id":"pair_9f8c99455b074c4ba04e52269613373d","disabled":true},{"name":"brand","value":"Brand3","description":"","id":"pair_dfd59b11102b48359233d874e56b5a45","disabled":true},{"name":"category_id","value":"9319747a-7fb3-4837-912c-02598d6325bd","description":"","id":"pair_78eb55aa4bdb4e1faca4fa1f80783d71","disabled":true}],"headers":[],"authentication":{},"metaSortKey":-1617238818213,"isPrivate":false,"settingStoreCookies":true,"settingSendCookies":true,"settingDisableRenderRequestBody":false,"settingEncodeUrl":true,"settingRebuildPath":true,"settingFollowRedirects":"global","_type":"request"},{"_id":"req_5d6e1f6a18874983a780624d3cd5eb87","parentId":"fld_f828e48755e146b3ad78fd933c6db81d","modified":1639665624627,"created":1617322641020,"url":"{{baseURL}}/rentals","name":"Create","description":"","method":"POST","body":{"mimeType":"application/json","text":"{\n\t\"car_id\": \"16f0f3e5-e572-4250-9a9e-5360af20c3b5\",\n\t\"expected_return_date\": \"2021-12-17T10:31:46.145Z\"\n}"},"parameters":[],"headers":[{"name":"Content-Type","value":"application/json","id":"pair_68be32dd95894a2a8e48d619990ed313"}],"authentication":{"type":"bearer","token":"{{userToken}}"},"metaSortKey":-1617322641020,"isPrivate":false,"settingStoreCookies":true,"settingSendCookies":true,"settingDisableRenderRequestBody":false,"settingEncodeUrl":true,"settingRebuildPath":true,"settingFollowRedirects":"global","_type":"request"},{"_id":"fld_f828e48755e146b3ad78fd933c6db81d","parentId":"wrk_c323334f50894ea5bf086585c0dc8307","modified":1617670485859,"created":1617322638174,"name":"Rents","description":"","environment":{"resource":"rents"},"environmentPropertyOrder":{"&":["resource"]},"metaSortKey":-1616147932682.5,"_type":"request_group"},{"_id":"req_c351f35d784f4dd086b8ce4c9d83421c","parentId":"fld_f828e48755e146b3ad78fd933c6db81d","modified":1633111004402,"created":1617673479489,"url":"{{baseURL}}/rentals/devolution/941bed07-dc4f-4ce3-8354-228069da59c2","name":"Devolution","description":"","method":"POST","body":{},"parameters":[],"headers":[],"authentication":{"type":"bearer","token":"{{adminToken}}"},"metaSortKey":-1617322640970,"isPrivate":false,"settingStoreCookies":true,"settingSendCookies":true,"settingDisableRenderRequestBody":false,"settingEncodeUrl":true,"settingRebuildPath":true,"settingFollowRedirects":"global","_type":"request"},{"_id":"req_b8e43b29686b4fb5a1bb216dc607320e","parentId":"fld_f828e48755e146b3ad78fd933c6db81d","modified":1633110996856,"created":1617674940719,"url":"{{baseURL}}/{{resource}}/user","name":"List All By User","description":"","method":"GET","body":{},"parameters":[{"name":"name","value":"","description":"","id":"pair_9f8c99455b074c4ba04e52269613373d","disabled":true}],"headers":[],"authentication":{"type":"bearer","token":"{{userToken}}"},"metaSortKey":-1617322640920,"isPrivate":false,"settingStoreCookies":true,"settingSendCookies":true,"settingDisableRenderRequestBody":false,"settingEncodeUrl":true,"settingRebuildPath":true,"settingFollowRedirects":"global","_type":"request"},{"_id":"req_7403d20b89024f3fac0127aba87667f3","parentId":"fld_c8e412e47c344250ae17799e12ce1f55","modified":1643925770071,"created":1615829129072,"url":"{{baseURL}}/{{resource}}","name":"Create","description":"","method":"POST","body":{"mimeType":"application/json","text":"{\n\t\"name\": \"C칙mbio autom치tic1o\",\n\t\"description\": \"Carro com c칙mbio autom치tico\"\n}  "},"parameters":[],"headers":[{"name":"Content-Type","value":"application/json","id":"pair_66006c2171ac4f91bcd103c7d6dba66f"}],"authentication":{"type":"bearer","token":"{{adminToken}}"},"metaSortKey":-1615829129072,"isPrivate":false,"settingStoreCookies":true,"settingSendCookies":true,"settingDisableRenderRequestBody":false,"settingEncodeUrl":true,"settingRebuildPath":true,"settingFollowRedirects":"global","_type":"request"},{"_id":"fld_c8e412e47c344250ae17799e12ce1f55","parentId":"wrk_c323334f50894ea5bf086585c0dc8307","modified":1615829123775,"created":1615829103488,"name":"Specifications","description":"","environment":{"resource":"specifications"},"environmentPropertyOrder":{"&":["resource"]},"metaSortKey":-1615829103488,"_type":"request_group"},{"_id":"env_3707db0fefb53bb9d89cecbb94fd8d1e8438a51b","parentId":"wrk_c323334f50894ea5bf086585c0dc8307","modified":1615823156142,"created":1615823156142,"name":"Base Environment","data":{},"dataPropertyOrder":null,"color":null,"isPrivate":false,"metaSortKey":1615823156142,"_type":"environment"},{"_id":"jar_3707db0fefb53bb9d89cecbb94fd8d1e8438a51b","parentId":"wrk_c323334f50894ea5bf086585c0dc8307","modified":1615823156143,"created":1615823156143,"name":"Default Jar","cookies":[],"_type":"cookie_jar"},{"_id":"spc_a483deec64be4b83b81b74bcabbb9711","parentId":"wrk_c323334f50894ea5bf086585c0dc8307","modified":1615823156053,"created":1615823156053,"fileName":"RentalX","contents":"","contentType":"yaml","_type":"api_spec"},{"_id":"env_24c65ee45acc458f90501228ba97864a","parentId":"env_3707db0fefb53bb9d89cecbb94fd8d1e8438a51b","modified":1639072356627,"created":1615823178669,"name":"Dev","data":{"baseURL":"http://localhost:3333","userToken":"{% response 'body', 'req_027c24f4796e45548af76c1306293b0a', 'b64::JC50b2tlbg==::46b', 'no-history', 60 %}","adminToken":"{% response 'body', 'req_b167990393c84eacb04535acb5b7ed19', 'b64::JC50b2tlbg==::46b', 'no-history', 60 %}"},"dataPropertyOrder":{"&":["baseURL","userToken","adminToken"]},"color":"#00ff08","isPrivate":false,"metaSortKey":1615823178669,"_type":"environment"}]}
